dls_bxflow_epsic/__init__.py
dls_bxflow_epsic/__main__.py
dls_bxflow_epsic/_version.py
dls_bxflow_epsic/epsic_main.py
dls_bxflow_epsic/epsic_workflow.py
dls_bxflow_epsic/utilities.py
dls_bxflow_epsic/version.py
dls_bxflow_epsic/algorithms/__init__.py
dls_bxflow_epsic/algorithms/mib_converter.py
dls_bxflow_epsic/collectors/__init__.py
dls_bxflow_epsic/collectors/mib_scraper.py
dls_bxflow_epsic-1.2.0.dist-info/LICENSE
dls_bxflow_epsic-1.2.0.dist-info/METADATA
dls_bxflow_epsic-1.2.0.dist-info/WHEEL
dls_bxflow_epsic-1.2.0.dist-info/entry_points.txt
dls_bxflow_epsic-1.2.0.dist-info/top_level.txt
dls_bxflow_epsic-1.2.0.dist-info/RECORD
